main.py
setup.py
batchran.egg-info/PKG-INFO
batchran.egg-info/SOURCES.txt
batchran.egg-info/dependency_links.txt
batchran.egg-info/requires.txt
batchran.egg-info/top_level.txt